{
  "nom_voyageur": "Yann",
  "destination_principale": "Kyoto",
  "duree_voyage": "2 jours",
  "budget_estime": "Non précisé",
  "type_voyage": "solo - explore",
  "resume_complet": "Yann, un voyageur passionné, a prévu un séjour de 2 jours à Kyoto à partir du 11 octobre 2025. Ce voyage, centré sur l'exploration en solo, adopte un rythme équilibré, permettant à Yann de découvrir à son propre rythme les temples emblématiques de la ville. Bien qu'aucun budget n'ait été spécifié, il souhaite bénéficier de services tels que des restaurants, un logement confortable, une accommodation adaptée et des options de transport pour faciliter ses déplacements. Ce voyage promet d'être une immersion enrichissante dans la culture et l'histoire de Kyoto."
}